chessboard/__init__.py
chessboard/board.py
chessboard/constants.py
chessboard/display.py
chessboard/fenparser.py
chessboard/pieces.py
chessboard/utils.py
chessboard/images/bB.png
chessboard/images/bK.png
chessboard/images/bN.png
chessboard/images/bP.png
chessboard/images/bQ.png
chessboard/images/bR.png
chessboard/images/btile.png
chessboard/images/wB.png
chessboard/images/wK.png
chessboard/images/wN.png
chessboard/images/wP.png
chessboard/images/wQ.png
chessboard/images/wR.png
chessboard/images/wtile.png
chess_board-0.4.1.dist-info/LICENSE
chess_board-0.4.1.dist-info/METADATA
chess_board-0.4.1.dist-info/WHEEL
chess_board-0.4.1.dist-info/top_level.txt
chess_board-0.4.1.dist-info/RECORD
