Metadata-Version: 2.1
Name: chess-board
Version: 0.4.1
Summary: A python chessboard library for representing game positions.
Home-page: https://github.com/ahira-justice/chess-board
Author: Ahira Adefokun
Author-email: justiceahira@gmail.com
License: GPLv3
Classifier: License :: OSI Approved :: GNU General Public License v3 (GPLv3)
Classifier: Programming Language :: Python
Classifier: Programming Language :: Python :: 3
Classifier: Programming Language :: Python :: 3.6
Requires-Python: >=3.6.0
License-File: LICENSE
Requires-Dist: pygame
